pynhl/__init__.py
pynhl/classes.py
pynhl-0.6.3.dist-info/licenses/LICENSE
pynhl-0.6.3.dist-info/METADATA
pynhl-0.6.3.dist-info/WHEEL
pynhl-0.6.3.dist-info/top_level.txt
pynhl-0.6.3.dist-info/RECORD
