Metadata-Version: 2.4
Name: pynhl
Version: 0.6.3
Summary: Python wrapper for NHL API used in Home Assistant
Author-email: Jay Lowenthal <jasonlowenthal@live.com>
License-Expression: GPL-3.0-or-later
Project-URL: Homepage, https://github.com/JayBlackedOut/pynhl
Project-URL: Issues, https://github.com/JayBlackedOut/pynhl/issues
Classifier: Programming Language :: Python :: 3
Classifier: Operating System :: OS Independent
Requires-Python: >=3.9
License-File: LICENSE
Dynamic: license-file
